README.md
setup.py
amocrm_api/__init__.py
amocrm_api/base.py
amocrm_api/errors.py
amocrm_api/legacy_client.py
amocrm_api/oauth_client.py
amocrm_api_wrapper.egg-info/PKG-INFO
amocrm_api_wrapper.egg-info/SOURCES.txt
amocrm_api_wrapper.egg-info/dependency_links.txt
amocrm_api_wrapper.egg-info/requires.txt
amocrm_api_wrapper.egg-info/top_level.txt