Metadata-Version: 2.1
Name: amocrm-api-wrapper
Version: 0.0.14
Summary: Amocrm api wrapper v4
Home-page: https://github.com/bzdvdn/amocrm-api-wrapper
Author: bzdvdn
Author-email: bzdv.dn@gmail.com
License: MIT
Platform: UNKNOWN
Requires-Python: >=3.6
